{
  "id": "1545427",
  "name": "demo",
  "font_family": "iconfont",
  "css_prefix_text": "icon-",
  "description": "",
  "glyphs": [
    {
      "icon_id": "303626",
      "name": "全部订单",
      "font_class": "quanbudingdan",
      "unicode": "e66d",
      "unicode_decimal": 58989
    },
    {
      "icon_id": "485744",
      "name": "待付 款",
      "font_class": "daifukuan",
      "unicode": "e607",
      "unicode_decimal": 58887
    },
    {
      "icon_id": "551965",
      "name": "箭头",
      "font_class": "arrow-right-copy-copy",
      "unicode": "e603",
      "unicode_decimal": 58883
    },
    {
      "icon_id": "799781",
      "name": "配送地址",
      "font_class": "peisongdizhi",
      "unicode": "e615",
      "unicode_decimal": 58901
    },
    {
      "icon_id": "1836617",
      "name": "收藏职位",
      "font_class": "shoucangzhiwei",
      "unicode": "e611",
      "unicode_decimal": 58897
    },
    {
      "icon_id": "1836665",
      "name": "预览简历",
      "font_class": "yulanjianli",
      "unicode": "e612",
      "unicode_decimal": 58898
    },
    {
      "icon_id": "2577752",
      "name": "待评价",
      "font_class": "daipingjia",
      "unicode": "e613",
      "unicode_decimal": 58899
    },
    {
      "icon_id": "2852605",
      "name": "我的",
      "font_class": "wode",
      "unicode": "e66f",
      "unicode_decimal": 58991
    },
    {
      "icon_id": "3027654",
      "name": "帮助中心",
      "font_class": "bangzhu",
      "unicode": "e652",
      "unicode_decimal": 58962
    },
    {
      "icon_id": "3316865",
      "name": "待发货",
      "font_class": "fahuotixing",
      "unicode": "e614",
      "unicode_decimal": 58900
    },
    {
      "icon_id": "3785210",
      "name": "分类",
      "font_class": "fenlei",
      "unicode": "e670",
      "unicode_decimal": 58992
    },
    {
      "icon_id": "4261074",
      "name": "热销爆款",
      "font_class": "rexiaobaokuan",
      "unicode": "e624",
      "unicode_decimal": 58916
    },
    {
      "icon_id": "4482979",
      "name": "首页",
      "font_class": "shouye",
      "unicode": "e681",
      "unicode_decimal": 59009
    },
    {
      "icon_id": "4893684",
      "name": "待收货",
      "font_class": "daishouhuo",
      "unicode": "e63b",
      "unicode_decimal": 58939
    },
    {
      "icon_id": "5501555",
      "name": "首页-选中",
      "font_class": "index",
      "unicode": "e600",
      "unicode_decimal": 58880
    },
    {
      "icon_id": "5911848",
      "name": "我 的",
      "font_class": "home",
      "unicode": "e608",
      "unicode_decimal": 58888
    },
    {
      "icon_id": "6856157",
      "name": "购物车",
      "font_class": "gouwuche1",
      "unicode": "e605",
      "unicode_decimal": 58885
    },
    {
      "icon_id": "7524619",
      "name": "右箭头",
      "font_class": "youjiantou",
      "unicode": "e770",
      "unicode_decimal": 59248
    },
    {
      "icon_id": "8129146",
      "name": "关于我们",
      "font_class": "wode-guanyuwomen",
      "unicode": "e602",
      "unicode_decimal": 58882
    },
    {
      "icon_id": "8629244",
      "name": "购物车",
      "font_class": "gouwuche",
      "unicode": "e669",
      "unicode_decimal": 58985
    },
    {
      "icon_id": "8948940",
      "name": "我 的",
      "font_class": "wode1",
      "unicode": "e606",
      "unicode_decimal": 58886
    },
    {
      "icon_id": "9134686",
      "name": "我 的",
      "font_class": "wodedangxuan",
      "unicode": "e609",
      "unicode_decimal": 58889
    },
    {
      "icon_id": "9719102",
      "name": "分类-选中",
      "font_class": "leimupinleifenleileibie",
      "unicode": "e601",
      "unicode_decimal": 58881
    },
    {
      "icon_id": "11791522",
      "name": "购物车",
      "font_class": "che",
      "unicode": "e604",
      "unicode_decimal": 58884
    }
  ]
}
